visualdiff/__init__.py
visualdiff/core.py
visualdiff/paths.py
visualdiff/version.py
visualdiff-0.3.4.dist-info/METADATA
visualdiff-0.3.4.dist-info/RECORD
visualdiff-0.3.4.dist-info/WHEEL
visualdiff-0.3.4.dist-info/dependency_links.txt
visualdiff-0.3.4.dist-info/top_level.txt
