Metadata-Version: 2.1
Name: visualdiff
Version: 0.3.4
Summary: Automate chrome browser render diffs for website testing
Home-page: https://github.com/dariosky/visualdiff
Author: Dario Varotto
Author-email: dario.varotto@gmail.com
License: MIT license
Keywords: visualdiff
Platform: UNKNOWN
Classifier: Development Status :: 4 - Beta
Classifier: Intended Audience :: Developers
Classifier: License :: OSI Approved :: MIT License
Classifier: Natural Language :: English
Classifier: Programming Language :: Python :: 3.6
Requires-Dist: pillow
Requires-Dist: pyppeteer
